<?xml version="1.0" encoding="UTF-8" standalone="yes"?>
<contentHaul xmlns:a="http://www.appian.com/ae/types/2009">
    <versionUuid>_a-0000e71b-9358-8000-6ea4-01ef9001ef90_23698</versionUuid>
    <rule>
        <name>getImageWithId</name>
        <uuid>_636f6e74656e74-0000d16d-c4b6-8000-c132-01000001000000000000867</uuid>
        <description></description>
        <parentUuid>_a-0000d516-ce42-8000-11d1-010000010000_544</parentUuid>
        <visibility>
            <advertise>false</advertise>
            <hierarchy>true</hierarchy>
            <indexable>true</indexable>
            <quota>false</quota>
            <searchable>true</searchable>
            <system>false</system>
            <unlogged>false</unlogged>
        </visibility>
        <definition>= if ( imageId = 1 , #"_636f6e74656e74-0000d16d-c4b6-8000-c132-01000001000000000000862" , if ( imageId = 2 , #"_636f6e74656e74-0000d16d-c4b6-8000-c132-01000001000000000000863" , if ( imageId = 3 , #"_636f6e74656e74-0000d16d-c4b6-8000-c132-01000001000000000000864" , if ( imageId = 1 , #"_636f6e74656e74-0000d16d-c4b6-8000-c132-01000001000000000000865" , if ( imageId = 0 , #"_636f6e74656e74-0000d16d-c4b6-8000-c132-01000001000000000000866" , #"_636f6e74656e74-0000d16d-c4b6-8000-c132-01000001000000000000862" ) ) ) ) )</definition>
        <namedTypedValue>
            <name>imageId</name>
            <type>
                <name>int</name>
                <namespace>http://www.w3.org/2001/XMLSchema</namespace>
            </type>
        </namedTypedValue>
        <preferredEditor>legacy</preferredEditor>
        <offlineEnabled>false</offlineEnabled>
    </rule>
    <roleMap public="true">
        <role inherit="true" allowForAll="false" name="readers">
            <users/>
            <groups/>
        </role>
        <role inherit="true" allowForAll="false" name="authors">
            <users/>
            <groups/>
        </role>
        <role inherit="true" allowForAll="false" name="administrators">
            <users/>
            <groups/>
        </role>
        <role inherit="false" allowForAll="false" name="denyReaders">
            <users/>
            <groups/>
        </role>
        <role inherit="false" allowForAll="false" name="denyAuthors">
            <users/>
            <groups/>
        </role>
        <role inherit="false" allowForAll="false" name="denyAdministrators">
            <users/>
            <groups/>
        </role>
    </roleMap>
    <history>
        <historyInfo versionUuid="_a-0000e71b-9358-8000-6ea4-01ef9001ef90_23698"/>
    </history>
</contentHaul>
